minitrino/__init__.py
minitrino/ansi.py
minitrino/cli.py
minitrino/py.typed
minitrino/settings.py
minitrino/shutdown.py
minitrino/utils.py
minitrino/cmd/__init__.py
minitrino/cmd/config.py
minitrino/cmd/down.py
minitrino/cmd/exec.py
minitrino/cmd/lib_install.py
minitrino/cmd/modules.py
minitrino/cmd/provision.py
minitrino/cmd/remove.py
minitrino/cmd/resources.py
minitrino/cmd/restart.py
minitrino/cmd/snapshot.py
minitrino/core/__init__.py
minitrino/core/context.py
minitrino/core/envvars.py
minitrino/core/errors.py
minitrino/core/library.py
minitrino/core/modules.py
minitrino/core/cluster/__init__.py
minitrino/core/cluster/cluster.py
minitrino/core/cluster/ops.py
minitrino/core/cluster/ports.py
minitrino/core/cluster/provisioner.py
minitrino/core/cluster/resource.py
minitrino/core/cluster/validator.py
minitrino/core/docker/__init__.py
minitrino/core/docker/socket.py
minitrino/core/docker/wrappers.py
minitrino/core/exec/__init__.py
minitrino/core/exec/cmd.py
minitrino/core/exec/container.py
minitrino/core/exec/host.py
minitrino/core/exec/result.py
minitrino/core/exec/utils.py
minitrino/core/logging/__init__.py
minitrino/core/logging/common.py
minitrino/core/logging/formatter.py
minitrino/core/logging/handler.py
minitrino/core/logging/levels.py
minitrino/core/logging/logger.py
minitrino/core/logging/sink.py
minitrino/core/logging/spinner.py
minitrino/core/logging/utils.py
minitrino-3.0.3.dist-info/licenses/LICENSE
minitrino-3.0.3.dist-info/METADATA
minitrino-3.0.3.dist-info/WHEEL
minitrino-3.0.3.dist-info/entry_points.txt
minitrino-3.0.3.dist-info/top_level.txt
minitrino-3.0.3.dist-info/RECORD
