Metadata-Version: 2.4
Name: minitrino
Version: 3.0.3
Summary: A command line tool that makes it easy to run modular Trino environments locally.
Author-email: Jeff Lester <jeff.lester.dev@gmail.com>
License: Apache-2.0
Project-URL: Homepage, https://github.com/jefflester/minitrino
Keywords: docker,minitrino,starburst,trino
Requires-Python: >=3.10.12
License-File: LICENSE
Requires-Dist: PyYAML>=6.0.1
Requires-Dist: click==8.3.1
Requires-Dist: docker==7.1.0
Requires-Dist: humanize
Requires-Dist: jsonschema>=4.18.0
Requires-Dist: python-dateutil
Requires-Dist: requests>=2.32.2
Requires-Dist: tabulate
Provides-Extra: dev
Requires-Dist: bandit; extra == "dev"
Requires-Dist: deptry; extra == "dev"
Requires-Dist: docformatter; extra == "dev"
Requires-Dist: mdformat; extra == "dev"
Requires-Dist: mdformat-gfm; extra == "dev"
Requires-Dist: mdformat-myst; extra == "dev"
Requires-Dist: mypy; extra == "dev"
Requires-Dist: pre-commit; extra == "dev"
Requires-Dist: pydocstyle; extra == "dev"
Requires-Dist: ruff; extra == "dev"
Requires-Dist: setuptools; extra == "dev"
Requires-Dist: tomli; extra == "dev"
Requires-Dist: types-click; extra == "dev"
Requires-Dist: types-docker; extra == "dev"
Requires-Dist: types-jsonschema; extra == "dev"
Requires-Dist: types-PyYAML; extra == "dev"
Requires-Dist: types-python-dateutil; extra == "dev"
Requires-Dist: types-setuptools; extra == "dev"
Requires-Dist: types-tabulate; extra == "dev"
Requires-Dist: vulture; extra == "dev"
Requires-Dist: wheel; extra == "dev"
Requires-Dist: yamllint; extra == "dev"
Provides-Extra: docs
Requires-Dist: ablog; extra == "docs"
Requires-Dist: myst_parser; extra == "docs"
Requires-Dist: numpydoc; extra == "docs"
Requires-Dist: pydata-sphinx-theme; extra == "docs"
Requires-Dist: sphinx; extra == "docs"
Requires-Dist: sphinx-click; extra == "docs"
Requires-Dist: sphinx-copybutton; extra == "docs"
Requires-Dist: sphinx-design; extra == "docs"
Requires-Dist: sphinx-favicon; extra == "docs"
Requires-Dist: sphinx-togglebutton; extra == "docs"
Requires-Dist: sphinxext-opengraph; extra == "docs"
Dynamic: license-file
